MANIFEST.in
README.md
gurobimh.c
gurobimh.pxd
gurobimh.pyx
setup.cfg
setup.py
gurobimh.egg-info/PKG-INFO
gurobimh.egg-info/SOURCES.txt
gurobimh.egg-info/dependency_links.txt
gurobimh.egg-info/requires.txt
gurobimh.egg-info/top_level.txt