Metadata-Version: 1.1
Name: gurobimh
Version: 2016.2
Summary: alternative python interface for the Gurobi optimization software
Home-page: https://github.com/supermihi/gurobimh
Author: Michael Helmling
Author-email: michaelhelmling@posteo.de
License: GPL3
Platform: UNKNOWN
Classifier: Development Status :: 3 - Alpha
Classifier: Intended Audience :: Science/Research
Classifier: License :: OSI Approved :: GNU General Public License v3 or later (GPLv3+)
Classifier: Operating System :: OS Independent
Classifier: Programming Language :: Python :: 2.7
Classifier: Programming Language :: Python :: 3
Classifier: Topic :: Scientific/Engineering :: Mathematics
